osmtags2rive/__init__.py
osmtags2rive/cli.py
osmtags2rive/constants.py
osmtags2rive/osmtags2rive.py
osmtags2rive-0.6.0.dist-info/LICENSE
osmtags2rive-0.6.0.dist-info/METADATA
osmtags2rive-0.6.0.dist-info/WHEEL
osmtags2rive-0.6.0.dist-info/entry_points.txt
osmtags2rive-0.6.0.dist-info/top_level.txt
osmtags2rive-0.6.0.dist-info/RECORD
