Metadata-Version: 2.1
Name: osmtags2rive
Version: 0.6.0
Summary: Convert of openstreetmap/id-tagging-schema to RiveScript, the Artificial Intelligence Scripting Language (alternative to AIML)
Home-page: https://github.com/fititnt/openstreetmap-tags-to-rivescript
Author: Emerson Rocha
Author-email: rocha@ieee.org
Project-URL: Bug Tracker, https://github.com/fititnt/openstreetmap-tags-to-rivescript/issues
Classifier: Programming Language :: Python :: 3
Classifier: License :: OSI Approved :: The Unlicense (Unlicense)
Classifier: Operating System :: OS Independent
Classifier: Typing :: Typed
Classifier: Topic :: Utilities
Requires-Python: >=3.7
License-File: LICENSE
